{"application_docker_ams_index.md":"8RpVDFM9","overview_index.md":"nssNFJHX","application_git_command_git_lfs.md":"YbpAow_v","gamedevelop_godot_index.md":"VtA1kz5J","application_git_github_github520.md":"zp55oK2H","application_git_github_github_credentials.md":"l8f2PH7x","application_vscodium_plugins_coding.md":"SdNaPA84","application_vscodium_index.md":"jVCCzvek","gamedevelop_websites_index.md":"jvpmrvMt","application_vscodium_plugins_beautify.md":"58jcLA7j","overview_conventional.md":"S54j_jOO","overview_antd.md":"VzvTFOrA","topic_android_flash_unlock bootloader.md":"qMXAnZLh","application_git_command_git_editor.md":"7fp6LMUE","topic_android_flash_index.md":"Lf2k6sYr","application_docker_index.md":"XHJa_odD","gamedevelop_unity_index.md":"GDcCKWGv","topic_android_magisk.md":"rID3-lHx","topic_chromeos_index.md":"0BKdmIth","gamedevelop_unity_hack_index.md":"K7sKgk9z","topic_android_xiaomi.md":"DqXjO1vz","topic_arch_index.md":"4wwGEm9a","topic_chromeos_installation.md":"4poBIc_B","topic_android_rom_kernel_index.md":"2NEmRp56","topic_android_rom_kernel_kernelsu.md":"xttoRJcE","topic_android_rom_system_rro_overlays.md":"CKRkOKYd","topic_android_index.md":"v7jibXS4","topic_arch_beautify_splash.md":"WBA_riwy","topic_arch_installation.md":"BhoBWSrv","topic_arch_ecs_installation.md":"QsjF2p4i","gamedevelop_unity_project_gitignoretemplate.md":"yfD32yU5","topic_windows_index.md":"GzXMBo9w","application_neovim_index.md":"MVdp1z2x","topic_android_root_payload_dumper.md":"V609ZsXV","topic_android_rom_gsi_index.md":"spxKulhw","topic_windows_virtual-machine_wsl2.md":"HnzwR8oy","index.md":"406T5LkX","topic_android_rom_kernel_compile.md":"gT_RHYPS","gamedevelop_unity_plugins_index.md":"nfmsI-jn","topic_arch_terminal.md":"NFvnKepW","topic_android_rom_gsi_flash.md":"oM0VuWuh","topic_android_rom_system_custom_recovery.md":"7yvcMZs4","topic_arch_beautify_zsh.md":"R6Wqa3l9","topic_arch_other.md":"7f-7LliE","application_git_index.md":"xXA6Lly1","topic_windows_beautify_nerd-fonts-supply.md":"3EFjYRtW","topic_arch_repos.md":"B45wAeqF","topic_android_rom_gsi_dsu.md":"k6KJldxU","application_git_command_git_branch.md":"na4B4s_R","topic_arch_special_fan.md":"U9DXAnxI","topic_windows_virtual-machine_hyper-v.md":"yp0lecVj"}
