{"application_vscodium_index.md":"611fa334","application_vscodium_plugins_coding.md":"9f711cd9","overview_index.md":"0b3667bd","application_vscodium_plugins_beautify.md":"64d1f564","overview_antd.md":"1eaa148e","overview_conventional.md":"96421387","topic_android_flash_index.md":"1dc4b815","topic_android_magisk.md":"c108f4f2","application_git_command_git_lfs.md":"f862096f","application_unity_index.md":"230e0c88","topic_android_rom_gsi_index.md":"1157ef9c","application_git_github_github520.md":"279ce5b6","topic_android_rom_gsi_flash.md":"14ac3dae","application_unity_hack_index.md":"75d37451","application_unity_plugins_index.md":"267d0c2d","application_docker_ams_index.md":"a6be1e93","topic_android_rom_gsi_dsu.md":"c81aecd8","application_git_command_git_branch.md":"db3271ed","application_neovim_index.md":"12cc252b","application_git_github_github_credentials.md":"8bae8125","topic_android_rom_kernel_compile.md":"d3c635d5","topic_windows_beautify_nerd-fonts-supply.md":"53b3bca8","application_git_index.md":"eb0c2427","topic_chromeos_installation.md":"1188518f","topic_android_index.md":"786d9f6b","application_docker_index.md":"226378d4","application_unity_project_gitignoretemplate.md":"a782a7f3","topic_android_rom_kernel_kernelsu.md":"73a6c241","topic_arch_special_fan.md":"a7dca98b","topic_android_rom_rro_overlays.md":"645b82af","topic_android_root_payload_dumper.md":"19cc4643","topic_arch_terminal.md":"2798192e","topic_arch_index.md":"87096b3b","topic_chromeos_index.md":"6c4f04e3","topic_arch_beautify_zsh.md":"eca045c8","topic_arch_beautify_splash.md":"823ca6fc","topic_windows_virtual-machine_hyper-v.md":"012ac58f","topic_windows_virtual-machine_wsl2.md":"2c3c133c","topic_windows_index.md":"eaa03af5","index.md":"0aac7100","topic_android_rom_kernel_index.md":"c8d736d3","topic_arch_installation.md":"6c937b85","topic_android_flash_unlock bootloader.md":"aebad773","topic_arch_other.md":"676108b3","topic_arch_repos.md":"8d955173","topic_android_xiaomi.md":"3580de2f"}
